{
  "dependencies": {
  },
  "name": "postfix",
  "maintainer_email": "youremail@example.com",
  "attributes": {
  },
  "license": "All rights reserved",
  "suggestions": {
  },
  "platforms": {
  },
  "maintainer": "me",
  "long_description": "Description\n===========\n\nRequirements\n============\n\nAttributes\n==========\n\nUsage\n=====\n\n",
  "version": "0.0.1",
  "recommendations": {
  },
  "recipes": {
  },
  "groupings": {
  },
  "conflicting": {
  },
  "replacing": {
  },
  "description": "Installs/Configures postfix",
  "providing": {
  }
}